unipose/__init__.py
unipose/__main__.py
unipose/client.py
unipose/recorder.py
unipose/server.py
unipose/viewer.py
unipose/original_docs/LICENSE.txt
unipose/original_docs/NOTICE.txt
unipose/original_docs/README.md
unipose/posenet/__init__.py
unipose/posenet/constants.py
unipose/posenet/decode.py
unipose/posenet/decode_multi.py
unipose/posenet/utils.py
unipose/posenet/converter/__init__.py
unipose/posenet/converter/tfjs2pytorch.py
unipose/posenet/converter/wget.py
unipose/posenet/models/__init__.py
unipose/posenet/models/mobilenet_v1.py
unipose/posenet/models/model_factory.py
unipose/screenshots/.gitkeep
unipose/sprites/paused.png
unipose/sprites/recording.png
unipose-1.0.8.dist-info/LICENSE
unipose-1.0.8.dist-info/METADATA
unipose-1.0.8.dist-info/WHEEL
unipose-1.0.8.dist-info/top_level.txt
unipose-1.0.8.dist-info/RECORD
