Metadata-Version: 2.1
Name: unipose
Version: 1.0.8
Summary: 2D Pose in Unity with Python backend
Home-page: https://github.com/Sanjay-Ganeshan/UniPose
Author: Julie Ganeshan
Author-email: HeavenlyQueen@outlook.com
License: UNKNOWN
Platform: UNKNOWN
Classifier: Programming Language :: Python :: 3
Classifier: License :: OSI Approved :: MIT License
Classifier: Operating System :: Microsoft :: Windows :: Windows 10
Requires-Python: >=3.7
Requires-Dist: opencv-python (>=4.2.0.34)
Requires-Dist: easydict (>=1.9)
Requires-Dist: tqdm (>=4.46.0)
Requires-Dist: numpy (>=1.18.4)
Requires-Dist: requests (>=2.23.0)
